{
  "editor.detectIndentation": false,
  "editor.formatOnSave": true,
  "editor.insertSpaces": true,
  "editor.suggestSelection": "first",
  "editor.tabSize": 2,
  "editor.tokenColorCustomizations": {
    "textMateRules": [
      {
        "scope": "string",
        "settings": {
          "foreground": "#FFFFFF"
        }
      }
    ]
  },
  "explorer.confirmDelete": false,
  "explorer.confirmDragAndDrop": false,
  "git.confirmSync": true,
  "security.workspace.trust.untrustedFiles": "newWindow",
  "terminal.integrated.fontFamily": "MesloLGS NF",
  "typescript.updateImportsOnFileMove.enabled": "always",
  "window.zoomLevel": 1,
  "workbench.colorCustomizations": {
    "activityBar.background": "#000000",
    "activityBar.foreground": "#00FFFF",
    "badge.background": "#000000",
    "badge.foreground": "#00FFFF",
    "button.background": "#000000",
    "button.foreground": "#00FFFF",
    "contrastBorder": "#00FFFF",
    "dropdown.background": "#000000",
    "dropdown.border": "#00FFFF",
    "dropdown.foreground": "#00FFFF",
    "dropdown.listBackground": "#000000",
    "editor.background": "#000000",
    "editor.foreground": "#00FFFF",
    "editorGroupHeader.tabsBackground": "#000000",
    "editorGroupHeader.tabsBorder": "#00FFFF",
    "editorOverviewRuler.border": "#00FFFF",
    "foreground": "#00FFFF",
    "input.background": "#000000",
    "input.border": "#00FFFF",
    "input.foreground": "#00FFFF",
    "list.activeSelectionBackground": "#00FFFF",
    "list.activeSelectionForeground": "#000000",
    "list.dropBackground": "#000000",
    "list.focusBackground": "#00FFFF",
    "markdown.preview.backgroundColor": "#000000",
    "markdown.preview.color": "#00FFFF",
    "markdown.preview.text": "#00FFFF",
    "menu.background": "#000000",
    "menu.foreground": "#00FFFF",
    "notifications.background": "#000000",
    "notifications.foreground": "#00FFFF",
    "quickInput.background": "#000000",
    "quickInput.foreground": "#00FFFF",
    "scrollbar.shadow": "#00FFFF",
    "scrollbarSlider.activeBackground": "#00FFFF",
    "scrollbarSlider.background": "#00FFFF",
    "scrollbarSlider.hoverBackground": "#00FFFF",
    "selection.background": "#000000",
    "sideBar.background": "#000000",
    "tab.activeBackground": "#00FFFF",
    "tab.activeForeground": "#000000",
    "tab.inactiveBackground": "#000000",
    "tab.inactiveForeground": "#00FFFF",
    "terminal.background": "#000000",
    "terminal.foreground": "#00FFFF",
    "titleBar.": "#00FFFF",
    "titleBar.activeBackground": "#000000",
    "titleBar.activeForeground": "#00FFFF",
    "titleBar.border": "#00FFFF",
    "widget.shadow": "#000000"
  },
  "workbench.iconTheme": "vscode-icons",
  "solidity.telemetry": false,
  "vim.normalModeKeyBindingsNonRecursive": [
    {
      "before": [
        "<space>"
      ],
      "commands": [
        "whichkey.show"
      ],
    }
  ]
}
